{
  "similar_texts": [
    [
      0.9851293657774179,
      {
        "TEXT_IND_in_marked_db": 21,
        "VECTOR": [
          0.5099,
          0.76,
          0.12,
          0.15083333333333335,
          0.08333333333333331,
          0.0,
          0.023731345819468664,
          0.0,
          0.0,
          0.04761229877898497,
          0.20515436088965497
        ]
      }
    ],
    [
      0.9851293657774179,
      {
        "TEXT_IND_in_marked_db": 22,
        "VECTOR": [
          0.5099,
          0.76,
          0.12,
          0.15083333333333335,
          0.08333333333333331,
          0.0,
          0.023731345819468664,
          0.0,
          0.0,
          0.04761229877898497,
          0.20515436088965497
        ]
      }
    ],
    [
      0.9851293657774179,
      {
        "TEXT_IND_in_marked_db": 23,
        "VECTOR": [
          0.5099,
          0.76,
          0.12,
          0.15083333333333335,
          0.08333333333333331,
          0.0,
          0.023731345819468664,
          0.0,
          0.0,
          0.04761229877898497,
          0.20515436088965497
        ]
      }
    ],
    [
      0.9851293657774179,
      {
        "TEXT_IND_in_marked_db": 24,
        "VECTOR": [
          0.5099,
          0.76,
          0.12,
          0.15083333333333335,
          0.08333333333333331,
          0.0,
          0.023731345819468664,
          0.0,
          0.0,
          0.04761229877898497,
          0.20515436088965497
        ]
      }
    ],
    [
      0.9851293657774179,
      {
        "TEXT_IND_in_marked_db": 25,
        "VECTOR": [
          0.5099,
          0.76,
          0.12,
          0.15083333333333335,
          0.08333333333333331,
          0.0,
          0.023731345819468664,
          0.0,
          0.0,
          0.04761229877898497,
          0.20515436088965497
        ]
      }
    ]
  ],
  "simiar_sentences": [
    [
      [
        1.0,
        {
          "sent_ind_in_marked_db": 0,
          "sent_vector": [
            0.0,
            0.0,
            0.0,
            0.0,
            0.0,
            0.0,
            0.20909090909090913
          ]
        }
      ],
      [
        1.0,
        {
          "sent_ind_in_marked_db": 9,
          "sent_vector": [
            0.0,
            0.0,
            0.0,
            0.0,
            0.0,
            0.0,
            0.22105263157894736
          ]
        }
      ],
      [
        1.0,
        {
          "sent_ind_in_marked_db": 17,
          "sent_vector": [
            0.0,
            0.0,
            0.0,
            0.0,
            0.0,
            0.0,
            0.2142857142857143
          ]
        }
      ],
      [
        1.0,
        {
          "sent_ind_in_marked_db": 21,
          "sent_vector": [
            0.0,
            0.0,
            0.0,
            0.0,
            0.0,
            0.0,
            0.1777777777777778
          ]
        }
      ],
      [
        1.0,
        {
          "sent_ind_in_marked_db": 23,
          "sent_vector": [
            0.0,
            0.0,
            0.0,
            0.0,
            0.0,
            0.0,
            0.22
          ]
        }
      ]
    ],
    [
      [
        1.0,
        {
          "sent_ind_in_marked_db": 0,
          "sent_vector": [
            0.0,
            0.0,
            0.0,
            0.0,
            0.0,
            0.0,
            0.20909090909090913
          ]
        }
      ],
      [
        1.0,
        {
          "sent_ind_in_marked_db": 9,
          "sent_vector": [
            0.0,
            0.0,
            0.0,
            0.0,
            0.0,
            0.0,
            0.22105263157894736
          ]
        }
      ],
      [
        1.0,
        {
          "sent_ind_in_marked_db": 17,
          "sent_vector": [
            0.0,
            0.0,
            0.0,
            0.0,
            0.0,
            0.0,
            0.2142857142857143
          ]
        }
      ],
      [
        1.0,
        {
          "sent_ind_in_marked_db": 21,
          "sent_vector": [
            0.0,
            0.0,
            0.0,
            0.0,
            0.0,
            0.0,
            0.1777777777777778
          ]
        }
      ],
      [
        1.0,
        {
          "sent_ind_in_marked_db": 23,
          "sent_vector": [
            0.0,
            0.0,
            0.0,
            0.0,
            0.0,
            0.0,
            0.22
          ]
        }
      ]
    ],
    [
      [
        0.9999232316290718,
        {
          "sent_ind_in_marked_db": 30,
          "sent_vector": [
            0.0,
            0.0,
            0.0,
            0.0,
            0.0,
            0.3410809193522841,
            0.2540540540540541
          ]
        }
      ],
      [
        0.9994911672734389,
        {
          "sent_ind_in_marked_db": 60,
          "sent_vector": [
            0.0,
            0.0,
            0.0,
            0.0,
            0.0,
            0.2005065396327602,
            0.16363636363636366
          ]
        }
      ],
      [
        0.9852067479659232,
        {
          "sent_ind_in_marked_db": 18,
          "sent_vector": [
            0.0,
            0.0,
            0.0,
            0.0,
            0.0,
            0.25587955177537897,
            0.1333333333333333
          ]
        }
      ],
      [
        0.9821129437850973,
        {
          "sent_ind_in_marked_db": 67,
          "sent_vector": [
            0.0,
            0.0,
            0.0,
            0.05809217057865184,
            0.0,
            0.3105428555942213,
            0.3133333333333333
          ]
        }
      ],
      [
        0.9734577730791447,
        {
          "sent_ind_in_marked_db": 29,
          "sent_vector": [
            0.0,
            0.0,
            0.0,
            0.0,
            0.0,
            0.35667902536280593,
            0.16000000000000003
          ]
        }
      ]
    ],
    [
      [
        0.9978018718357247,
        {
          "sent_ind_in_marked_db": 14,
          "sent_vector": [
            0.05555555555555556,
            0.0,
            0.06912763848250579,
            0.0,
            0.0,
            0.0,
            0.2823529411764706
          ]
        }
      ],
      [
        0.9702381299826708,
        {
          "sent_ind_in_marked_db": 40,
          "sent_vector": [
            0.0,
            0.0,
            0.08405800365978727,
            0.0,
            0.0,
            0.0,
            0.34
          ]
        }
      ],
      [
        0.9665330583764628,
        {
          "sent_ind_in_marked_db": 61,
          "sent_vector": [
            0.0,
            0.0,
            0.07919492322075343,
            0.0,
            0.0,
            0.0,
            0.2
          ]
        }
      ],
      [
        0.9627275188617174,
        {
          "sent_ind_in_marked_db": 13,
          "sent_vector": [
            0.047619047619047616,
            0.0,
            0.0,
            0.0,
            0.0,
            0.0,
            0.205
          ]
        }
      ],
      [
        0.9619961359563337,
        {
          "sent_ind_in_marked_db": 56,
          "sent_vector": [
            0.10714285714285712,
            0.0,
            0.0917492977984888,
            0.0,
            0.0,
            0.08619916746450187,
            0.2925925925925926
          ]
        }
      ]
    ],
    [
      [
        1.0,
        {
          "sent_ind_in_marked_db": 0,
          "sent_vector": [
            0.0,
            0.0,
            0.0,
            0.0,
            0.0,
            0.0,
            0.20909090909090913
          ]
        }
      ],
      [
        1.0,
        {
          "sent_ind_in_marked_db": 9,
          "sent_vector": [
            0.0,
            0.0,
            0.0,
            0.0,
            0.0,
            0.0,
            0.22105263157894736
          ]
        }
      ],
      [
        1.0,
        {
          "sent_ind_in_marked_db": 17,
          "sent_vector": [
            0.0,
            0.0,
            0.0,
            0.0,
            0.0,
            0.0,
            0.2142857142857143
          ]
        }
      ],
      [
        1.0,
        {
          "sent_ind_in_marked_db": 21,
          "sent_vector": [
            0.0,
            0.0,
            0.0,
            0.0,
            0.0,
            0.0,
            0.1777777777777778
          ]
        }
      ],
      [
        1.0,
        {
          "sent_ind_in_marked_db": 23,
          "sent_vector": [
            0.0,
            0.0,
            0.0,
            0.0,
            0.0,
            0.0,
            0.22
          ]
        }
      ]
    ],
    [
      [
        0.9228962783913371,
        {
          "sent_ind_in_marked_db": 43,
          "sent_vector": [
            0.0,
            0.0,
            0.0753396136897156,
            0.0753396136897156,
            0.0,
            0.0,
            0.1666666666666667
          ]
        }
      ],
      [
        0.8933280977431562,
        {
          "sent_ind_in_marked_db": 55,
          "sent_vector": [
            0.0,
            0.0,
            0.0572208024040625,
            0.1578167247370857,
            0.0,
            0.0,
            0.25
          ]
        }
      ],
      [
        0.8407369424883249,
        {
          "sent_ind_in_marked_db": 56,
          "sent_vector": [
            0.10714285714285712,
            0.0,
            0.0917492977984888,
            0.0,
            0.0,
            0.08619916746450187,
            0.2925925925925926
          ]
        }
      ],
      [
        0.8349894974432605,
        {
          "sent_ind_in_marked_db": 14,
          "sent_vector": [
            0.05555555555555556,
            0.0,
            0.06912763848250579,
            0.0,
            0.0,
            0.0,
            0.2823529411764706
          ]
        }
      ],
      [
        0.8246576207265726,
        {
          "sent_ind_in_marked_db": 74,
          "sent_vector": [
            0.0,
            0.0,
            0.0,
            0.09426207629869852,
            0.0,
            0.0,
            0.1545454545454545
          ]
        }
      ]
    ],
    [
      [
        1.0,
        {
          "sent_ind_in_marked_db": 0,
          "sent_vector": [
            0.0,
            0.0,
            0.0,
            0.0,
            0.0,
            0.0,
            0.20909090909090913
          ]
        }
      ],
      [
        1.0,
        {
          "sent_ind_in_marked_db": 9,
          "sent_vector": [
            0.0,
            0.0,
            0.0,
            0.0,
            0.0,
            0.0,
            0.22105263157894736
          ]
        }
      ],
      [
        1.0,
        {
          "sent_ind_in_marked_db": 17,
          "sent_vector": [
            0.0,
            0.0,
            0.0,
            0.0,
            0.0,
            0.0,
            0.2142857142857143
          ]
        }
      ],
      [
        1.0,
        {
          "sent_ind_in_marked_db": 21,
          "sent_vector": [
            0.0,
            0.0,
            0.0,
            0.0,
            0.0,
            0.0,
            0.1777777777777778
          ]
        }
      ],
      [
        1.0,
        {
          "sent_ind_in_marked_db": 23,
          "sent_vector": [
            0.0,
            0.0,
            0.0,
            0.0,
            0.0,
            0.0,
            0.22
          ]
        }
      ]
    ],
    [
      [
        0.9997588272552456,
        {
          "sent_ind_in_marked_db": 18,
          "sent_vector": [
            0.0,
            0.0,
            0.0,
            0.0,
            0.0,
            0.25587955177537897,
            0.1333333333333333
          ]
        }
      ],
      [
        0.9967490604868208,
        {
          "sent_ind_in_marked_db": 29,
          "sent_vector": [
            0.0,
            0.0,
            0.0,
            0.0,
            0.0,
            0.35667902536280593,
            0.16000000000000003
          ]
        }
      ],
      [
        0.9963098222813883,
        {
          "sent_ind_in_marked_db": 25,
          "sent_vector": [
            0.0,
            0.0,
            0.0,
            0.0,
            0.0,
            0.33917020866118625,
            0.15000000000000002
          ]
        }
      ],
      [
        0.9905115052343179,
        {
          "sent_ind_in_marked_db": 30,
          "sent_vector": [
            0.0,
            0.0,
            0.0,
            0.0,
            0.0,
            0.3410809193522841,
            0.2540540540540541
          ]
        }
      ],
      [
        0.9834547939354652,
        {
          "sent_ind_in_marked_db": 60,
          "sent_vector": [
            0.0,
            0.0,
            0.0,
            0.0,
            0.0,
            0.2005065396327602,
            0.16363636363636366
          ]
        }
      ]
    ],
    [
      [
        0.9912900409652423,
        {
          "sent_ind_in_marked_db": 53,
          "sent_vector": [
            0.0,
            0.047619047619047616,
            0.0,
            0.0640807416179989,
            0.0,
            0.3249517639466085,
            0.19
          ]
        }
      ],
      [
        0.9859250288509878,
        {
          "sent_ind_in_marked_db": 18,
          "sent_vector": [
            0.0,
            0.0,
            0.0,
            0.0,
            0.0,
            0.25587955177537897,
            0.1333333333333333
          ]
        }
      ],
      [
        0.9840731457134583,
        {
          "sent_ind_in_marked_db": 29,
          "sent_vector": [
            0.0,
            0.0,
            0.0,
            0.0,
            0.0,
            0.35667902536280593,
            0.16000000000000003
          ]
        }
      ],
      [
        0.9837402572816996,
        {
          "sent_ind_in_marked_db": 25,
          "sent_vector": [
            0.0,
            0.0,
            0.0,
            0.0,
            0.0,
            0.33917020866118625,
            0.15000000000000002
          ]
        }
      ],
      [
        0.9737772002140422,
        {
          "sent_ind_in_marked_db": 30,
          "sent_vector": [
            0.0,
            0.0,
            0.0,
            0.0,
            0.0,
            0.3410809193522841,
            0.2540540540540541
          ]
        }
      ]
    ]
  ],
  "similar_collocations": [
    [
      "группа вежливый отказ",
      []
    ],
    [
      "отмечать",
      [
        [
          {
            "marked_colloc_db_index": 285,
            "sim_colloc": "упоминать",
            "w2v_sim": 0.6693426539517813,
            "freqence_similarity": 0.9920021319131361
          },
          0.7338745495440523
        ]
      ]
    ],
    [
      "день свой рождение",
      []
    ],
    [
      "большой",
      [
        [
          {
            "marked_colloc_db_index": 334,
            "sim_colloc": "большой",
            "w2v_sim": 1.0000000000000004,
            "freqence_similarity": 1.0
          },
          1.0000000000000004
        ]
      ]
    ],
    [
      "концерт на сцена",
      []
    ],
    [
      "московский международный дом музыка",
      []
    ],
    [
      "ммдм",
      []
    ],
    [
      "выступление проходить",
      []
    ],
    [
      "1",
      []
    ],
    [
      "апрель сообщать лентеру",
      [
        [
          {
            "marked_colloc_db_index": 49,
            "sim_colloc": "сентябрь",
            "w2v_sim": 0.7928829733764791,
            "freqence_similarity": 0.9961000085207455
          },
          0.8335263804053324
        ]
      ]
    ],
    [
      "организатор",
      []
    ],
    [
      "по слово лидер",
      []
    ],
    [
      "команда",
      []
    ],
    [
      "роман",
      []
    ],
    [
      "суслов",
      []
    ],
    [
      "концерт проходить в",
      []
    ],
    [
      "полный",
      [
        [
          {
            "marked_colloc_db_index": 319,
            "sim_colloc": "полный",
            "w2v_sim": 1.0,
            "freqence_similarity": 1.0
          },
          1.0
        ]
      ]
    ],
    [
      "и даже",
      []
    ],
    [
      "переполненном состав",
      []
    ],
    [
      "он подчеркивать что",
      []
    ],
    [
      "хотя быть",
      []
    ],
    [
      "исполнять и старый песня",
      []
    ],
    [
      "выступление не",
      []
    ],
    [
      "становиться",
      [
        [
          {
            "marked_colloc_db_index": 0,
            "sim_colloc": "оказываться",
            "w2v_sim": 0.6643523822547825,
            "freqence_similarity": 0.9870533410854319
          },
          0.7288925740209125
        ]
      ]
    ],
    [
      "ностальгический",
      []
    ],
    [
      "группа представлять слушатель",
      []
    ],
    [
      "новый материал",
      []
    ],
    [
      "кроме то в",
      []
    ],
    [
      "программа",
      []
    ],
    [
      "входить",
      [
        [
          {
            "marked_colloc_db_index": 113,
            "sim_colloc": "входить",
            "w2v_sim": 1.0000000000000004,
            "freqence_similarity": 1.0
          },
          1.0000000000000004
        ]
      ]
    ],
    [
      "некоторый",
      [
        [
          {
            "marked_colloc_db_index": 11,
            "sim_colloc": "который",
            "w2v_sim": 0.7433834958079364,
            "freqence_similarity": 0.9616392370003215
          },
          0.7870346440464135
        ],
        [
          {
            "marked_colloc_db_index": 149,
            "sim_colloc": "который",
            "w2v_sim": 0.7433834958079364,
            "freqence_similarity": 0.9616392370003215
          },
          0.7870346440464135
        ],
        [
          {
            "marked_colloc_db_index": 165,
            "sim_colloc": "который",
            "w2v_sim": 0.7433834958079364,
            "freqence_similarity": 0.9616392370003215
          },
          0.7870346440464135
        ],
        [
          {
            "marked_colloc_db_index": 236,
            "sim_colloc": "который",
            "w2v_sim": 0.7433834958079364,
            "freqence_similarity": 0.9616392370003215
          },
          0.7870346440464135
        ]
      ]
    ],
    [
      "композиция",
      [
        [
          {
            "marked_colloc_db_index": 192,
            "sim_colloc": "композиция",
            "w2v_sim": 1.0000000000000009,
            "freqence_similarity": 0.9999999999999998
          },
          1.0000000000000007
        ]
      ]
    ],
    [
      "давно не",
      []
    ],
    [
      "исполняться",
      []
    ],
    [
      "с сцена",
      []
    ],
    [
      "группа вежливый отказ",
      []
    ],
    [
      "образовываться в 1985 год",
      []
    ],
    [
      "в москва",
      []
    ],
    [
      "в 1986 год",
      []
    ],
    [
      "выходить",
      [
        [
          {
            "marked_colloc_db_index": 113,
            "sim_colloc": "входить",
            "w2v_sim": 0.6558791105558853,
            "freqence_similarity": 0.9994401241231297
          },
          0.7245913132693342
        ],
        [
          {
            "marked_colloc_db_index": 141,
            "sim_colloc": "ходить",
            "w2v_sim": 0.7000021978641566,
            "freqence_similarity": 0.4926553185237678
          },
          0.6585328219960789
        ]
      ]
    ],
    [
      "первый альб коллектив",
      []
    ],
    [
      "опер",
      []
    ],
    [
      "86",
      []
    ],
    [
      "последний на сегодняшний день",
      []
    ],
    [
      "альб коллектив гуся",
      []
    ],
    [
      "лебеди",
      []
    ],
    [
      "быть",
      [
        [
          {
            "marked_colloc_db_index": 19,
            "sim_colloc": "быть",
            "w2v_sim": 0.9999999999999998,
            "freqence_similarity": 1.0000000000000002
          },
          0.9999999999999999
        ],
        [
          {
            "marked_colloc_db_index": 46,
            "sim_colloc": "быть",
            "w2v_sim": 0.9999999999999998,
            "freqence_similarity": 1.0000000000000002
          },
          0.9999999999999999
        ],
        [
          {
            "marked_colloc_db_index": 78,
            "sim_colloc": "быть",
            "w2v_sim": 0.9999999999999998,
            "freqence_similarity": 1.0000000000000002
          },
          0.9999999999999999
        ],
        [
          {
            "marked_colloc_db_index": 312,
            "sim_colloc": "быть",
            "w2v_sim": 0.9999999999999998,
            "freqence_similarity": 1.0000000000000002
          },
          0.9999999999999999
        ]
      ]
    ],
    [
      "выпускать в 2010 год",
      []
    ]
  ]
}